agenticmem/__init__.py
agenticmem/cache.py
agenticmem/client.py
agenticmem/client_utils.py
agenticmem-0.1.4.4.dist-info/METADATA
agenticmem-0.1.4.4.dist-info/WHEEL
agenticmem-0.1.4.4.dist-info/RECORD
