Metadata-Version: 2.3
Name: agenticmem
Version: 0.1.4.4
Summary: A Python client for the AgenticMem API
License: MIT
Author: AgenticMem Team
Requires-Python: >=3.10,<4.0
Classifier: License :: OSI Approved :: MIT License
Classifier: Programming Language :: Python :: 3
Classifier: Programming Language :: Python :: 3.10
Classifier: Programming Language :: Python :: 3.11
Classifier: Programming Language :: Python :: 3.12
Classifier: Programming Language :: Python :: 3.13
Requires-Dist: agenticmem-commons (==0.1.4.4)
Requires-Dist: aiohttp (>=3.12.9,<4.0.0)
Requires-Dist: griffe (==0.48.0)
Requires-Dist: mkdocs-with-pdf (>=0.9.3,<0.10.0)
Requires-Dist: mkdocstrings[python] (>=0.18.0)
Requires-Dist: pydantic (>=2.0.0,<3.0.0)
Requires-Dist: python-dateutil (>=2.8.0,<3.0.0)
Requires-Dist: requests (>=2.25.0,<3.0.0)
Requires-Dist: weasyprint (>=66.0,<67.0)
